{
  "domains": {
    "fema.gov": {
      "count": 11,
      "first_seen": "2026-06-25",
      "last_seen": "2026-06-27"
    },
    "nfwf.org": {
      "count": 10,
      "first_seen": "2026-06-25",
      "last_seen": "2026-06-28"
    },
    "epa.gov": {
      "count": 2,
      "first_seen": "2026-06-25",
      "last_seen": "2026-06-25"
    },
    "new.nsf.gov": {
      "count": 2,
      "first_seen": "2026-06-25",
      "last_seen": "2026-06-25"
    },
    "ukri.org": {
      "count": 1,
      "first_seen": "2026-06-25",
      "last_seen": "2026-06-25"
    },
    "research-and-innovation.ec.europa.eu": {
      "count": 8,
      "first_seen": "2026-06-25",
      "last_seen": "2026-06-28"
    },
    "rea.ec.europa.eu": {
      "count": 5,
      "first_seen": "2026-06-25",
      "last_seen": "2026-06-26"
    },
    "climate-kic.org": {
      "count": 1,
      "first_seen": "2026-06-25",
      "last_seen": "2026-06-25"
    },
    "grants.gov": {
      "count": 447,
      "first_seen": "2026-06-25",
      "last_seen": "2026-06-28"
    },
    "floodcoalition.org": {
      "count": 1,
      "first_seen": "2026-06-25",
      "last_seen": "2026-06-25"
    },
    "simpler.grants.gov": {
      "count": 2,
      "first_seen": "2026-06-25",
      "last_seen": "2026-06-26"
    },
    "www2.fundsforngos.org": {
      "count": 8,
      "first_seen": "2026-06-25",
      "last_seen": "2026-06-27"
    },
    "floridadep.gov": {
      "count": 11,
      "first_seen": "2026-06-25",
      "last_seen": "2026-06-28"
    },
    "dec.ny.gov": {
      "count": 2,
      "first_seen": "2026-06-25",
      "last_seen": "2026-06-26"
    },
    "nfuonline.com": {
      "count": 1,
      "first_seen": "2026-06-25",
      "last_seen": "2026-06-25"
    },
    "projects.research-and-innovation.ec.europa.eu": {
      "count": 2,
      "first_seen": "2026-06-25",
      "last_seen": "2026-06-25"
    },
    "ec.europa.eu": {
      "count": 1,
      "first_seen": "2026-06-25",
      "last_seen": "2026-06-25"
    },
    "adb.org": {
      "count": 15,
      "first_seen": "2026-06-25",
      "last_seen": "2026-06-28"
    },
    "greenclimate.fund": {
      "count": 4,
      "first_seen": "2026-06-25",
      "last_seen": "2026-06-28"
    },
    "housing-infrastructure.canada.ca": {
      "count": 5,
      "first_seen": "2026-06-25",
      "last_seen": "2026-06-26"
    },
    "cinea.ec.europa.eu": {
      "count": 4,
      "first_seen": "2026-06-25",
      "last_seen": "2026-06-27"
    },
    "governor.ny.gov": {
      "count": 2,
      "first_seen": "2026-06-26",
      "last_seen": "2026-06-26"
    },
    "twdb.texas.gov": {
      "count": 1,
      "first_seen": "2026-06-26",
      "last_seen": "2026-06-26"
    },
    "iuk-business-connect.org.uk": {
      "count": 2,
      "first_seen": "2026-06-26",
      "last_seen": "2026-06-28"
    },
    "mission-adaptation-portal.ec.europa.eu": {
      "count": 3,
      "first_seen": "2026-06-26",
      "last_seen": "2026-06-27"
    },
    "scc.ca.gov": {
      "count": 2,
      "first_seen": "2026-06-26",
      "last_seen": "2026-06-26"
    },
    "nature.org": {
      "count": 2,
      "first_seen": "2026-06-26",
      "last_seen": "2026-06-26"
    },
    "watershed.la.gov": {
      "count": 2,
      "first_seen": "2026-06-26",
      "last_seen": "2026-06-26"
    },
    "water.ca.gov": {
      "count": 1,
      "first_seen": "2026-06-26",
      "last_seen": "2026-06-26"
    },
    "recovery.texas.gov": {
      "count": 1,
      "first_seen": "2026-06-26",
      "last_seen": "2026-06-26"
    },
    "scientifyresearch.org": {
      "count": 2,
      "first_seen": "2026-06-26",
      "last_seen": "2026-06-26"
    },
    "errin.eu": {
      "count": 2,
      "first_seen": "2026-06-26",
      "last_seen": "2026-06-26"
    },
    "lao.ca.gov": {
      "count": 1,
      "first_seen": "2026-06-26",
      "last_seen": "2026-06-26"
    },
    "westmed-initiative.ec.europa.eu": {
      "count": 1,
      "first_seen": "2026-06-26",
      "last_seen": "2026-06-26"
    },
    "texasfloodclearinghouse.org": {
      "count": 1,
      "first_seen": "2026-06-26",
      "last_seen": "2026-06-26"
    },
    "eic.ec.europa.eu": {
      "count": 4,
      "first_seen": "2026-06-26",
      "last_seen": "2026-06-28"
    },
    "eo4society.esa.int": {
      "count": 3,
      "first_seen": "2026-06-26",
      "last_seen": "2026-06-28"
    },
    "interreg-danube.eu": {
      "count": 1,
      "first_seen": "2026-06-26",
      "last_seen": "2026-06-26"
    },
    "gov.uk": {
      "count": 1,
      "first_seen": "2026-06-26",
      "last_seen": "2026-06-26"
    },
    "fundsforcompanies.fundsforngos.org": {
      "count": 2,
      "first_seen": "2026-06-27",
      "last_seen": "2026-06-27"
    },
    "horizoneuropencpportal.eu": {
      "count": 1,
      "first_seen": "2026-06-28",
      "last_seen": "2026-06-28"
    },
    "greenmunicipalfund.ca": {
      "count": 2,
      "first_seen": "2026-06-28",
      "last_seen": "2026-06-28"
    },
    "nwo.nl": {
      "count": 1,
      "first_seen": "2026-06-28",
      "last_seen": "2026-06-28"
    },
    "business.esa.int": {
      "count": 1,
      "first_seen": "2026-06-28",
      "last_seen": "2026-06-28"
    }
  }
}